[
  {
    "id": "59f45d2dcda1edbc9d77d8cc9826f6094deb1da29918903741641fe3bdc2730b",
    "hash": "59f45d2dcda1edbc9d77d8cc9826f6094deb1da29918903741641fe3bdc2730b",
    "txid": "59f45d2dcda1edbc9d77d8cc9826f6094deb1da29918903741641fe3bdc2730b",
    "url": "peertube://peertube160.pocketnet.app/f8f663ea-2180-4299-872b-30a35ffaab13",
    "resolutions": [],
    "uploader": "MySpeech",
    "uploaderAddress": "PJrkM3z5MZgjMeWFCTnuMHtYi5UrWZTCP7",
    "uploaderAvatar": "https://peertube601.pocketnet.app/images/78535c183af5b1b303639778edf94a6a/78535c183af5b1b303639778edf94a6a-original.jpg",
    "uploaderReputation": 722,
    "description": "Идиомы",
    "duration": 57,
    "timestamp": "2025-07-25T16:03:35.000Z",
    "formattedDate": "7/25/2025",
    "likes": 0,
    "comments": 0,
    "ratingsCount": 0,
    "averageRating": 0,
    "userRating": 0,
    "commentData": [],
    "type": "video",
    "tags": [
      "englishidioms",
      "learningenglish",
      "knowledgeispower",
      "share",
      "englishwithgalinakhalyuko",
      "myspeech",
      "английскиеидиомы",
      "youtubeканалmyspeech",
      "myspeechchannel",
      "telegram_myspeech",
      "мойспичканал",
      "myspeech27",
      "englishwithmyspeech",
      "education",
      "swag"
    ],
    "language": "de",
    "hasVideo": true,
    "videoInfo": {
      "peertube": {
        "instance": "peertube160.pocketnet.app",
        "uuid": "f8f663ea-2180-4299-872b-30a35ffaab13",
        "durationSeconds": 57,
        "hlsUrl": "https://peertube160.pocketnet.app/static/streaming-playlists/hls/f8f663ea-2180-4299-872b-30a35ffaab13/ab8a54e9-1e5a-49d3-a987-97cca5b42700-master.m3u8",
        "apiUrl": "https://peertube160.pocketnet.app/api/v1/videos/f8f663ea-2180-4299-872b-30a35ffaab13"
      }
    },
    "rawPost": {
      "video_hash": "59f45d2dcda1edbc9d77d8cc9826f6094deb1da29918903741641fe3bdc2730b",
      "bastyon_post_link": "https://bastyon.com/post?s=59f45d2dcda1edbc9d77d8cc9826f6094deb1da29918903741641fe3bdc2730b",
      "author_address": "PJrkM3z5MZgjMeWFCTnuMHtYi5UrWZTCP7",
      "caption": "Идиомы",
      "description": "\nМой телеграмм канал https://t.me/moispeech\nЯ в инстаграме myspeech27\nЯ во VK Fleur De-Lina https://vk.com/idlifeisgood1990\nЯ в ОК https://ok.ru//profile/575835999463\nЯ в Youtube http://www.youtube.com/@galinahalukowa2836\nЯ в Likee @speech27\nЯ в Bastyon bastyon://myspeech?ref=pjrkm3z5mzgjmewfc…\nЯ в Rutube https://rutube.ru/channel/37847294/\n\n#englishidioms #learningenglish #knowledgeispower #share #englishwithgalinakhalyukova #myspeech #английскиеидиомы #youtubeканалmyspeech #myspeechChannel #telegram_myspeech #myspeech #мойспичканал #myspeech27 #englishwithmyspeech #education Н513ВУ\n#swag #instalike #instamood\n#likeforlike #лайктайм #likeback #лайкнименя #like4like #репост\n#outfit #fashion #style",
      "hashtags": "[\"englishidioms\",\"learningenglish\",\"knowledgeispower\",\"share\",\"englishwithgalinakhalyuko\",\"myspeech\",\"английскиеидиомы\",\"youtubeканалmyspeech\",\"myspeechchannel\",\"telegram_myspeech\",\"мойспичканал\",\"myspeech27\",\"englishwithmyspeech\",\"education\",\"swag\"]",
      "video_url": "peertube://peertube160.pocketnet.app/f8f663ea-2180-4299-872b-30a35ffaab13",
      "block_height": 3393639,
      "timestamp": 1753459415,
      "language": "de",
      "author_reputation": 722,
      "tx_id": 137765463,
      "author_name": "MySpeech",
      "author_avatar": "https://peertube601.pocketnet.app/images/78535c183af5b1b303639778edf94a6a/78535c183af5b1b303639778edf94a6a-original.jpg",
      "peertube": {
        "instance": "peertube160.pocketnet.app",
        "uuid": "f8f663ea-2180-4299-872b-30a35ffaab13",
        "durationSeconds": 57,
        "hlsUrl": "https://peertube160.pocketnet.app/static/streaming-playlists/hls/f8f663ea-2180-4299-872b-30a35ffaab13/ab8a54e9-1e5a-49d3-a987-97cca5b42700-master.m3u8",
        "apiUrl": "https://peertube160.pocketnet.app/api/v1/videos/f8f663ea-2180-4299-872b-30a35ffaab13"
      },
      "comments_count": 0,
      "comments": []
    },
    "bastyonPostLink": "https://bastyon.com/post?s=59f45d2dcda1edbc9d77d8cc9826f6094deb1da29918903741641fe3bdc2730b"
  },
  {
    "id": "051fd689f0d66aaf92971d52fadb45af185527e6fc2d8b788cf7726d8369a7f3",
    "hash": "051fd689f0d66aaf92971d52fadb45af185527e6fc2d8b788cf7726d8369a7f3",
    "txid": "051fd689f0d66aaf92971d52fadb45af185527e6fc2d8b788cf7726d8369a7f3",
    "url": "peertube://peertube160.pocketnet.app/8e54cd77-8532-40c9-b749-8c0393b30bb0",
    "resolutions": [],
    "uploader": "MySpeech",
    "uploaderAddress": "PJrkM3z5MZgjMeWFCTnuMHtYi5UrWZTCP7",
    "uploaderAvatar": "https://peertube601.pocketnet.app/images/78535c183af5b1b303639778edf94a6a/78535c183af5b1b303639778edf94a6a-original.jpg",
    "uploaderReputation": 722,
    "description": "Полезные фразы на итальянском языке по теме \"Покупки\"",
    "duration": 73,
    "timestamp": "2025-07-23T09:51:18.000Z",
    "formattedDate": "7/23/2025",
    "likes": 0,
    "comments": 2,
    "ratingsCount": 0,
    "averageRating": 0,
    "userRating": 0,
    "commentData": [],
    "type": "video",
    "tags": [
      "englishidioms",
      "learningenglish",
      "knowledgeispower",
      "share",
      "englishwithgalinakhalyuko",
      "myspeech",
      "английскиеидиомы",
      "youtubeканалmyspeech",
      "myspeechchannel",
      "telegram_myspeech",
      "мойспичканал",
      "myspeech27",
      "englishwithmyspeech",
      "education",
      "swag"
    ],
    "language": "de",
    "hasVideo": true,
    "videoInfo": {
      "peertube": {
        "instance": "peertube160.pocketnet.app",
        "uuid": "8e54cd77-8532-40c9-b749-8c0393b30bb0",
        "durationSeconds": 73,
        "hlsUrl": "https://peertube160.pocketnet.app/static/streaming-playlists/hls/8e54cd77-8532-40c9-b749-8c0393b30bb0/054c58ed-28fc-4273-b405-f740330313f7-master.m3u8",
        "apiUrl": "https://peertube160.pocketnet.app/api/v1/videos/8e54cd77-8532-40c9-b749-8c0393b30bb0"
      }
    },
    "rawPost": {
      "video_hash": "051fd689f0d66aaf92971d52fadb45af185527e6fc2d8b788cf7726d8369a7f3",
      "bastyon_post_link": "https://bastyon.com/post?s=051fd689f0d66aaf92971d52fadb45af185527e6fc2d8b788cf7726d8369a7f3",
      "author_address": "PJrkM3z5MZgjMeWFCTnuMHtYi5UrWZTCP7",
      "caption": "Полезные фразы на итальянском языке по теме \"Покупки\"",
      "description": "Мой телеграмм канал https://t.me/moispeech\nЯ в инстаграме myspeech27\nЯ во VK Fleur De-Lina https://vk.com/idlifeisgood1990\nЯ в ОК https://ok.ru//profile/575835999463\nЯ в Youtube http://www.youtube.com/@galinahalukowa2836\nЯ в Likee @speech27\nЯ в Bastyon bastyon://myspeech?ref=pjrkm3z5mzgjmewfc…\nЯ в Rutube https://rutube.ru/channel/37847294/\n\n#englishidioms #learningenglish #knowledgeispower #share #englishwithgalinakhalyukova #myspeech #английскиеидиомы #youtubeканалmyspeech #myspeechChannel #telegram_myspeech #myspeech #мойспичканал #myspeech27 #englishwithmyspeech #education Н513ВУ\n#swag #instalike #instamood\n#likeforlike #лайктайм #likeback #лайкнименя #like4like #репост\n#outfit #fashion #style",
      "hashtags": "[\"englishidioms\",\"learningenglish\",\"knowledgeispower\",\"share\",\"englishwithgalinakhalyuko\",\"myspeech\",\"английскиеидиомы\",\"youtubeканалmyspeech\",\"myspeechchannel\",\"telegram_myspeech\",\"мойспичканал\",\"myspeech27\",\"englishwithmyspeech\",\"education\",\"swag\"]",
      "video_url": "peertube://peertube160.pocketnet.app/8e54cd77-8532-40c9-b749-8c0393b30bb0",
      "block_height": 3390199,
      "timestamp": 1753264278,
      "language": "de",
      "author_reputation": 722,
      "tx_id": 137425225,
      "author_name": "MySpeech",
      "author_avatar": "https://peertube601.pocketnet.app/images/78535c183af5b1b303639778edf94a6a/78535c183af5b1b303639778edf94a6a-original.jpg",
      "peertube": {
        "instance": "peertube160.pocketnet.app",
        "uuid": "8e54cd77-8532-40c9-b749-8c0393b30bb0",
        "durationSeconds": 73,
        "hlsUrl": "https://peertube160.pocketnet.app/static/streaming-playlists/hls/8e54cd77-8532-40c9-b749-8c0393b30bb0/054c58ed-28fc-4273-b405-f740330313f7-master.m3u8",
        "apiUrl": "https://peertube160.pocketnet.app/api/v1/videos/8e54cd77-8532-40c9-b749-8c0393b30bb0"
      },
      "comments_count": 2,
      "comments": [
        {
          "comment_tx_id": 137446655,
          "comment_hash_id": 137446655,
          "video_tx_id": 137425225,
          "author_id": 69728924,
          "parent_comment_tx_id": null,
          "answer_comment_tx_id": null,
          "message": "{\"message\":\"Molto interessante 😜\",\"url\":\"\",\"images\":[],\"info\":\"\"}",
          "timestamp": 1753273594,
          "block_height": 3390355,
          "likes": 1,
          "dislikes": 0,
          "author_address": "PCmLFV4Ra8hAdqaqTFRdgJ2d6tLtXMt2Fu",
          "author_name": "Autumnal_Pianist",
          "author_avatar": "https://peertube800.pocketnet.app/images/a13dd47e9cb549bf4c3819005ca10766/a13dd47e9cb549bf4c3819005ca10766-original.jpg",
          "author_reputation": 8056
        },
        {
          "comment_tx_id": 137449773,
          "comment_hash_id": 137449773,
          "video_tx_id": 137425225,
          "author_id": 89298705,
          "parent_comment_tx_id": 137446655,
          "answer_comment_tx_id": 137446655,
          "message": "{\"message\":\"@Autumnal_Pianist, Grazie🙂\",\"url\":\"\",\"images\":[],\"info\":\"\"}",
          "timestamp": 1753274851,
          "block_height": 3390376,
          "likes": 0,
          "dislikes": 0,
          "author_address": "PJrkM3z5MZgjMeWFCTnuMHtYi5UrWZTCP7",
          "author_name": "MySpeech",
          "author_avatar": "https://peertube601.pocketnet.app/images/78535c183af5b1b303639778edf94a6a/78535c183af5b1b303639778edf94a6a-original.jpg",
          "author_reputation": 722
        }
      ]
    },
    "bastyonPostLink": "https://bastyon.com/post?s=051fd689f0d66aaf92971d52fadb45af185527e6fc2d8b788cf7726d8369a7f3"
  },
  {
    "id": "0338b881c4e62e5e817e46aa0bfb12fbd86a5cf7019626bc4dc30f81193a3929",
    "hash": "0338b881c4e62e5e817e46aa0bfb12fbd86a5cf7019626bc4dc30f81193a3929",
    "txid": "0338b881c4e62e5e817e46aa0bfb12fbd86a5cf7019626bc4dc30f81193a3929",
    "url": "peertube://peertube160.pocketnet.app/b851da76-ac97-432a-9f53-c46a3053a1cf",
    "resolutions": [],
    "uploader": "MySpeech",
    "uploaderAddress": "PJrkM3z5MZgjMeWFCTnuMHtYi5UrWZTCP7",
    "uploaderAvatar": "https://peertube601.pocketnet.app/images/78535c183af5b1b303639778edf94a6a/78535c183af5b1b303639778edf94a6a-original.jpg",
    "uploaderReputation": 722,
    "description": "Das Café. Кафе",
    "duration": 111,
    "timestamp": "2025-07-13T17:26:10.000Z",
    "formattedDate": "7/13/2025",
    "likes": 0,
    "comments": 0,
    "ratingsCount": 0,
    "averageRating": 0,
    "userRating": 0,
    "commentData": [],
    "type": "video",
    "tags": [
      "englishidioms",
      "learningenglish",
      "knowledgeispower",
      "share",
      "englishwithgalinakhalyuko",
      "myspeech",
      "английскиеидиомы",
      "youtubeканалmyspeech",
      "myspeechchannel",
      "telegram_myspeech",
      "мойспичканал",
      "myspeech27",
      "englishwithmyspeech",
      "education",
      "swag"
    ],
    "language": "de",
    "hasVideo": true,
    "videoInfo": {
      "peertube": {
        "instance": "peertube160.pocketnet.app",
        "uuid": "b851da76-ac97-432a-9f53-c46a3053a1cf",
        "durationSeconds": 111,
        "hlsUrl": "https://peertube160.pocketnet.app/static/streaming-playlists/hls/b851da76-ac97-432a-9f53-c46a3053a1cf/2c7e399f-168a-440b-ab04-d6461fef2f3a-master.m3u8",
        "apiUrl": "https://peertube160.pocketnet.app/api/v1/videos/b851da76-ac97-432a-9f53-c46a3053a1cf"
      }
    },
    "rawPost": {
      "video_hash": "0338b881c4e62e5e817e46aa0bfb12fbd86a5cf7019626bc4dc30f81193a3929",
      "bastyon_post_link": "https://bastyon.com/post?s=0338b881c4e62e5e817e46aa0bfb12fbd86a5cf7019626bc4dc30f81193a3929",
      "author_address": "PJrkM3z5MZgjMeWFCTnuMHtYi5UrWZTCP7",
      "caption": "Das Café. Кафе",
      "description": "\nМой телеграмм канал https://t.me/moispeech\nЯ в инстаграме myspeech27\nЯ во VK Fleur De-Lina https://vk.com/idlifeisgood1990\nЯ в ОК https://ok.ru//profile/575835999463\nЯ в Youtube http://www.youtube.com/@galinahalukowa2836\nЯ в Likee @speech27\nЯ в Bastyon bastyon://myspeech?ref=pjrkm3z5mzgjmewfc…\nЯ в Rutube https://rutube.ru/channel/37847294/\n\n#englishidioms #learningenglish #knowledgeispower #share #englishwithgalinakhalyukova #myspeech #английскиеидиомы #youtubeканалmyspeech #myspeechChannel #telegram_myspeech #myspeech #мойспичканал #myspeech27 #englishwithmyspeech #education Н513ВУ\n#swag #instalike #instamood\n#likeforlike #лайктайм #likeback #лайкнименя #like4like #репост\n#outfit #fashion #style",
      "hashtags": "[\"englishidioms\",\"learningenglish\",\"knowledgeispower\",\"share\",\"englishwithgalinakhalyuko\",\"myspeech\",\"английскиеидиомы\",\"youtubeканалmyspeech\",\"myspeechchannel\",\"telegram_myspeech\",\"мойспичканал\",\"myspeech27\",\"englishwithmyspeech\",\"education\",\"swag\"]",
      "video_url": "peertube://peertube160.pocketnet.app/b851da76-ac97-432a-9f53-c46a3053a1cf",
      "block_height": 3375957,
      "timestamp": 1752427570,
      "language": "de",
      "author_reputation": 722,
      "tx_id": 135972853,
      "author_name": "MySpeech",
      "author_avatar": "https://peertube601.pocketnet.app/images/78535c183af5b1b303639778edf94a6a/78535c183af5b1b303639778edf94a6a-original.jpg",
      "peertube": {
        "instance": "peertube160.pocketnet.app",
        "uuid": "b851da76-ac97-432a-9f53-c46a3053a1cf",
        "durationSeconds": 111,
        "hlsUrl": "https://peertube160.pocketnet.app/static/streaming-playlists/hls/b851da76-ac97-432a-9f53-c46a3053a1cf/2c7e399f-168a-440b-ab04-d6461fef2f3a-master.m3u8",
        "apiUrl": "https://peertube160.pocketnet.app/api/v1/videos/b851da76-ac97-432a-9f53-c46a3053a1cf"
      },
      "comments_count": 0,
      "comments": []
    },
    "bastyonPostLink": "https://bastyon.com/post?s=0338b881c4e62e5e817e46aa0bfb12fbd86a5cf7019626bc4dc30f81193a3929"
  },
  {
    "id": "0ff1c3a69c5610880cb5c33a83c62d58adae987fa7fb24e298a482a370ab4f0e",
    "hash": "0ff1c3a69c5610880cb5c33a83c62d58adae987fa7fb24e298a482a370ab4f0e",
    "txid": "0ff1c3a69c5610880cb5c33a83c62d58adae987fa7fb24e298a482a370ab4f0e",
    "url": "peertube://peertube160.pocketnet.app/693b46b8-acbd-442e-856d-43a3598cc364",
    "resolutions": [],
    "uploader": "Kritiker",
    "uploaderAddress": "PVZiCTxWzKZLNrZ9LEZSUmvLEwWYaXWd3P",
    "uploaderAvatar": "https://i.imgur.com/TiMPDhn.jpeg",
    "uploaderReputation": 4664,
    "description": "Alles Heuchler und Lügner",
    "duration": 70,
    "timestamp": "2025-07-12T19:53:40.000Z",
    "formattedDate": "7/12/2025",
    "likes": 0,
    "comments": 2,
    "ratingsCount": 0,
    "averageRating": 0,
    "userRating": 0,
    "commentData": [],
    "type": "video",
    "tags": [
      "propaganda",
      "afd",
      "weidel",
      "wehrpflicht",
      "israel",
      "digitalisierung",
      "genozid",
      "ekelerregend",
      "pervers",
      "wahnsinnig",
      "niederträchtig"
    ],
    "language": "de",
    "hasVideo": true,
    "videoInfo": {
      "peertube": {
        "instance": "peertube160.pocketnet.app",
        "uuid": "693b46b8-acbd-442e-856d-43a3598cc364",
        "durationSeconds": 70,
        "hlsUrl": "https://peertube160.pocketnet.app/static/streaming-playlists/hls/693b46b8-acbd-442e-856d-43a3598cc364/83d058ab-3f72-4439-a8ce-41733e0ce646-master.m3u8",
        "apiUrl": "https://peertube160.pocketnet.app/api/v1/videos/693b46b8-acbd-442e-856d-43a3598cc364"
      }
    },
    "rawPost": {
      "video_hash": "0ff1c3a69c5610880cb5c33a83c62d58adae987fa7fb24e298a482a370ab4f0e",
      "bastyon_post_link": "https://bastyon.com/post?s=0ff1c3a69c5610880cb5c33a83c62d58adae987fa7fb24e298a482a370ab4f0e",
      "author_address": "PVZiCTxWzKZLNrZ9LEZSUmvLEwWYaXWd3P",
      "caption": "Alles Heuchler und Lügner",
      "description": "Magnet macht wieder Propaganda für Weidel und die AFD und die Zwangsherrschaft !!!\n\nWarum will Weidel auch das wir 5% des BIP für den Krieg ausgeben? Warum will sie die Wehrpflicht? Warum tut die AFD alles für die Digitalisierung ? Warum ist Weidel und der AFD Israel so wichtig und sie steht voll dahinter und redet nicht über den Genozid in Gaza und vieles mehr?\n\nWarum berichten Magnet und AUF1 niemals kritisch über die AFD? Warum darf er im Bundestag Weidel interviewen, wo ihn das böse System doch angeblich so bekämpf? Weil er Fake und gesteuerte Opposition ist. Erwartet keine wirklich kritischen Fragen an Weidel. Es wird wieder nur Propaganda. Magnet wird sich wieder wie ein unterwürfiges Schoßhündchen benehmen.\n\nWarum verschweigt Magnet das über Weidel beharrlich, obwohl es viral ging?\n\nDiese AFD gehört genauso zum System wie ALLE Parteien in der BRiD. 🤷♂",
      "hashtags": "[\"propaganda\",\"afd\",\"weidel\",\"wehrpflicht\",\"israel\",\"digitalisierung\",\"genozid\",\"ekelerregend\",\"pervers\",\"wahnsinnig\",\"niederträchtig\"]",
      "video_url": "peertube://peertube160.pocketnet.app/693b46b8-acbd-442e-856d-43a3598cc364",
      "block_height": 3374656,
      "timestamp": 1752350020,
      "language": "de",
      "author_reputation": 4664,
      "tx_id": 135847172,
      "author_name": "Kritiker",
      "author_avatar": "https://i.imgur.com/TiMPDhn.jpeg",
      "peertube": {
        "instance": "peertube160.pocketnet.app",
        "uuid": "693b46b8-acbd-442e-856d-43a3598cc364",
        "durationSeconds": 70,
        "hlsUrl": "https://peertube160.pocketnet.app/static/streaming-playlists/hls/693b46b8-acbd-442e-856d-43a3598cc364/83d058ab-3f72-4439-a8ce-41733e0ce646-master.m3u8",
        "apiUrl": "https://peertube160.pocketnet.app/api/v1/videos/693b46b8-acbd-442e-856d-43a3598cc364"
      },
      "comments_count": 2,
      "comments": [
        {
          "comment_tx_id": 135972633,
          "comment_hash_id": 135972633,
          "video_tx_id": 135847172,
          "author_id": 94253158,
          "parent_comment_tx_id": null,
          "answer_comment_tx_id": null,
          "message": "{\"message\":\"Genauso ist es, die AfD gehört genauso zum System wie auch alle anderen Parteien bzw. Firmen.\\nDie AfD ist ebenso wie alle anderen Parteien in den internationalen Firmen.- und Handelsregister als Unternehmen registriert und besitzt somit eine DUNS-Nummer.\\nDie AfD ist meiner Meinung nach keine Alternative für Deutschland, sondern faktisch eine Alternative aus Israel, welche die Interessen der Zionisten vertritt.\\nDoch nicht alleine nur das zionistische Netanjahu-Regime ist der AfD wohlgesonnen, sondern bekanntlich auch die Zionisten aus der Trump-Administration.\\nDie jüdische Zionistin Weidel hat jahrelang bei Goldman Sachs gearbeitet, also für die jüdisch-zionistische Hochfinanz.\\nBekanntlich ebenfalls auch der jüdische Zionist Merz, welcher jahrelang Cheflobbyist bei BlackRock Deutschland war.\",\"url\":\"\",\"images\":[],\"info\":\"\"}",
          "timestamp": 1752427507,
          "block_height": 3375957,
          "likes": 1,
          "dislikes": 0,
          "author_address": "PEaYrbWJ1M3DMwYsHLAm4C3hHHmWjdgyWL",
          "author_name": "House737",
          "author_avatar": "",
          "author_reputation": null
        },
        {
          "comment_tx_id": 135973470,
          "comment_hash_id": 135973470,
          "video_tx_id": 135847172,
          "author_id": 94253158,
          "parent_comment_tx_id": null,
          "answer_comment_tx_id": null,
          "message": "{\"message\":\"Insofern kann man daraus leicht ableiten weshalb diese Herrschaften ganz bereitwillig nun 5% von unserem BIP jährlich für die Rüstung ausgeben wollen.\\nDenn schließlich gehören die meisten Firmenanteile der Rüstungskonzerne letztendlich BlackRock und Vanguard, den Investmentfondsgesellschaften der jüdisch-zionistischen Hochfinanz.\",\"url\":\"\",\"images\":[],\"info\":\"\"}",
          "timestamp": 1752427845,
          "block_height": 3375963,
          "likes": 0,
          "dislikes": 0,
          "author_address": "PEaYrbWJ1M3DMwYsHLAm4C3hHHmWjdgyWL",
          "author_name": "House737",
          "author_avatar": "",
          "author_reputation": null
        }
      ]
    },
    "bastyonPostLink": "https://bastyon.com/post?s=0ff1c3a69c5610880cb5c33a83c62d58adae987fa7fb24e298a482a370ab4f0e"
  },
  {
    "id": "726cbf47f74de352bce646e763a8c72a86a18289cd16425b02a351686e01a4a5",
    "hash": "726cbf47f74de352bce646e763a8c72a86a18289cd16425b02a351686e01a4a5",
    "txid": "726cbf47f74de352bce646e763a8c72a86a18289cd16425b02a351686e01a4a5",
    "url": "peertube://peertube160.pocketnet.app/bd8edb78-8b65-4f49-a6b2-ac823c378941",
    "resolutions": [],
    "uploader": "Irenaktiw",
    "uploaderAddress": "PLFGVpoRYCxA55ziNwjdU2eo5HBaet5UzG",
    "uploaderAvatar": "https://peertube700.pocketnet.app/images/9db4ea1dda8ed8e4873abc6567fc9c37/9db4ea1dda8ed8e4873abc6567fc9c37-original.jpg",
    "uploaderReputation": 19095,
    "description": "Настоящие товарищи  Одна из пчел застряла в липкой подкормке, но её друзья этого так не оставили.",
    "duration": 27,
    "timestamp": "2025-07-10T05:55:10.000Z",
    "formattedDate": "7/10/2025",
    "likes": 0,
    "comments": 4,
    "ratingsCount": 0,
    "averageRating": 0,
    "userRating": 0,
    "commentData": [],
    "type": "video",
    "tags": [
      "natur",
      "tiere",
      "природа",
      "товарищи",
      "жизнь",
      "энергия"
    ],
    "language": "de",
    "hasVideo": true,
    "videoInfo": {
      "peertube": {
        "instance": "peertube160.pocketnet.app",
        "uuid": "bd8edb78-8b65-4f49-a6b2-ac823c378941",
        "durationSeconds": 27,
        "hlsUrl": "https://peertube160.pocketnet.app/static/streaming-playlists/hls/bd8edb78-8b65-4f49-a6b2-ac823c378941/8a620678-6d42-4dde-9892-00d74a7149f3-master.m3u8",
        "apiUrl": "https://peertube160.pocketnet.app/api/v1/videos/bd8edb78-8b65-4f49-a6b2-ac823c378941"
      }
    },
    "rawPost": {
      "video_hash": "726cbf47f74de352bce646e763a8c72a86a18289cd16425b02a351686e01a4a5",
      "bastyon_post_link": "https://bastyon.com/post?s=726cbf47f74de352bce646e763a8c72a86a18289cd16425b02a351686e01a4a5",
      "author_address": "PLFGVpoRYCxA55ziNwjdU2eo5HBaet5UzG",
      "caption": "Настоящие товарищи  Одна из пчел застряла в липкой подкормке, но её друзья этого так не оставили.",
      "description": "Природа. Из чата Творение.",
      "hashtags": "[\"natur\",\"tiere\",\"природа\",\"товарищи\",\"жизнь\",\"энергия\"]",
      "video_url": "peertube://peertube160.pocketnet.app/bd8edb78-8b65-4f49-a6b2-ac823c378941",
      "block_height": 3370890,
      "timestamp": 1752126910,
      "language": "de",
      "author_reputation": 19095,
      "tx_id": 135470917,
      "author_name": "Irenaktiw",
      "author_avatar": "https://peertube700.pocketnet.app/images/9db4ea1dda8ed8e4873abc6567fc9c37/9db4ea1dda8ed8e4873abc6567fc9c37-original.jpg",
      "peertube": {
        "instance": "peertube160.pocketnet.app",
        "uuid": "bd8edb78-8b65-4f49-a6b2-ac823c378941",
        "durationSeconds": 27,
        "hlsUrl": "https://peertube160.pocketnet.app/static/streaming-playlists/hls/bd8edb78-8b65-4f49-a6b2-ac823c378941/8a620678-6d42-4dde-9892-00d74a7149f3-master.m3u8",
        "apiUrl": "https://peertube160.pocketnet.app/api/v1/videos/bd8edb78-8b65-4f49-a6b2-ac823c378941"
      },
      "comments_count": 4,
      "comments": [
        {
          "comment_tx_id": 135471815,
          "comment_hash_id": 135471815,
          "video_tx_id": 135470917,
          "author_id": 72412207,
          "parent_comment_tx_id": null,
          "answer_comment_tx_id": null,
          "message": "{\"message\":\"👍👍👍 умнички!\",\"url\":\"\",\"images\":[],\"info\":\"\"}",
          "timestamp": 1752127324,
          "block_height": 3370896,
          "likes": 1,
          "dislikes": 0,
          "author_address": "PKz9dt5AZFsEyH4rU4qdWiWm1triEs6Zoi",
          "author_name": "Elenavakto",
          "author_avatar": "https://bastyon.com:8092/i/FjLTPmegoXARaVNSvIKOYY.jfif",
          "author_reputation": 275046
        },
        {
          "comment_tx_id": 135477938,
          "comment_hash_id": 135477938,
          "video_tx_id": 135470917,
          "author_id": 87787602,
          "parent_comment_tx_id": 135471815,
          "answer_comment_tx_id": 135471815,
          "message": "{\"message\":\"@Elenavakto, 🫶\",\"url\":\"\",\"images\":[],\"info\":\"\"}",
          "timestamp": 1752130544,
          "block_height": 3370941,
          "likes": 1,
          "dislikes": 0,
          "author_address": "PLFGVpoRYCxA55ziNwjdU2eo5HBaet5UzG",
          "author_name": "Irenaktiw",
          "author_avatar": "https://peertube700.pocketnet.app/images/9db4ea1dda8ed8e4873abc6567fc9c37/9db4ea1dda8ed8e4873abc6567fc9c37-original.jpg",
          "author_reputation": 19095
        },
        {
          "comment_tx_id": 135536717,
          "comment_hash_id": 135536717,
          "video_tx_id": 135470917,
          "author_id": 62569937,
          "parent_comment_tx_id": null,
          "answer_comment_tx_id": null,
          "message": "{\"message\":\"Красавцы!🤝👍🤓\",\"url\":\"\",\"images\":[],\"info\":\"\"}",
          "timestamp": 1752158294,
          "block_height": 3371424,
          "likes": 0,
          "dislikes": 0,
          "author_address": "PWGVFU7P9PHkWTFFZkWCrvKbjvDNNkVkCZ",
          "author_name": "AKMTRUD2025",
          "author_avatar": "https://peertube160.pocketnet.app/images/528a2647338cea6f8534f838bac6c4dd/528a2647338cea6f8534f838bac6c4dd-original.jpg",
          "author_reputation": 40158
        },
        {
          "comment_tx_id": 135603743,
          "comment_hash_id": 135603743,
          "video_tx_id": 135470917,
          "author_id": 73717064,
          "parent_comment_tx_id": null,
          "answer_comment_tx_id": null,
          "message": "{\"message\":\"💗👍🌿🍀🌿👍🌷🌷🌷🌷🌷\",\"url\":\"\",\"images\":[],\"info\":\"\"}",
          "timestamp": 1752203776,
          "block_height": 3372191,
          "likes": 1,
          "dislikes": 0,
          "author_address": "PFUyJYnsGBhq4aRvykNHkPv1cnWVVgpKdj",
          "author_name": "Svettika",
          "author_avatar": "https://peertube800.pocketnet.app/images/abcb3d5373f5c3c2e11fafba4db3b457/abcb3d5373f5c3c2e11fafba4db3b457-original.jpg",
          "author_reputation": 381540
        }
      ]
    },
    "bastyonPostLink": "https://bastyon.com/post?s=726cbf47f74de352bce646e763a8c72a86a18289cd16425b02a351686e01a4a5"
  },
  {
    "id": "49b48db85cc7b1a9eb1b90343fe3507c50e8a9a20730f7ee3b5c21c423ef454c",
    "hash": "49b48db85cc7b1a9eb1b90343fe3507c50e8a9a20730f7ee3b5c21c423ef454c",
    "txid": "49b48db85cc7b1a9eb1b90343fe3507c50e8a9a20730f7ee3b5c21c423ef454c",
    "url": "peertube://peertube160.pocketnet.app/6b93423c-531b-4ca6-9ae9-2cf9d84ca41d",
    "resolutions": [],
    "uploader": "Irenaktiw",
    "uploaderAddress": "PLFGVpoRYCxA55ziNwjdU2eo5HBaet5UzG",
    "uploaderAvatar": "https://peertube700.pocketnet.app/images/9db4ea1dda8ed8e4873abc6567fc9c37/9db4ea1dda8ed8e4873abc6567fc9c37-original.jpg",
    "uploaderReputation": 19095,
    "description": "Новая эра ИИ: Не верь всему, что видишь.  Скоро будет не отличить от реальности. ",
    "duration": 32,
    "timestamp": "2025-07-09T04:59:12.000Z",
    "formattedDate": "7/9/2025",
    "likes": 0,
    "comments": 3,
    "ratingsCount": 0,
    "averageRating": 0,
    "userRating": 0,
    "commentData": [],
    "type": "video",
    "tags": [
      "интересно",
      "ии"
    ],
    "language": "de",
    "hasVideo": true,
    "videoInfo": {
      "peertube": {
        "instance": "peertube160.pocketnet.app",
        "uuid": "6b93423c-531b-4ca6-9ae9-2cf9d84ca41d",
        "durationSeconds": 32,
        "hlsUrl": "https://peertube160.pocketnet.app/static/streaming-playlists/hls/6b93423c-531b-4ca6-9ae9-2cf9d84ca41d/1cee7e04-ff53-44b4-b954-84235d357a80-master.m3u8",
        "apiUrl": "https://peertube160.pocketnet.app/api/v1/videos/6b93423c-531b-4ca6-9ae9-2cf9d84ca41d"
      }
    },
    "rawPost": {
      "video_hash": "49b48db85cc7b1a9eb1b90343fe3507c50e8a9a20730f7ee3b5c21c423ef454c",
      "bastyon_post_link": "https://bastyon.com/post?s=49b48db85cc7b1a9eb1b90343fe3507c50e8a9a20730f7ee3b5c21c423ef454c",
      "author_address": "PLFGVpoRYCxA55ziNwjdU2eo5HBaet5UzG",
      "caption": "Новая эра ИИ: Не верь всему, что видишь.  Скоро будет не отличить от реальности. ",
      "description": "Из чата Творение.",
      "hashtags": "[\"интересно\",\"ии\"]",
      "video_url": "peertube://peertube160.pocketnet.app/6b93423c-531b-4ca6-9ae9-2cf9d84ca41d",
      "block_height": 3369363,
      "timestamp": 1752037152,
      "language": "de",
      "author_reputation": 19095,
      "tx_id": 135318479,
      "author_name": "Irenaktiw",
      "author_avatar": "https://peertube700.pocketnet.app/images/9db4ea1dda8ed8e4873abc6567fc9c37/9db4ea1dda8ed8e4873abc6567fc9c37-original.jpg",
      "peertube": {
        "instance": "peertube160.pocketnet.app",
        "uuid": "6b93423c-531b-4ca6-9ae9-2cf9d84ca41d",
        "durationSeconds": 32,
        "hlsUrl": "https://peertube160.pocketnet.app/static/streaming-playlists/hls/6b93423c-531b-4ca6-9ae9-2cf9d84ca41d/1cee7e04-ff53-44b4-b954-84235d357a80-master.m3u8",
        "apiUrl": "https://peertube160.pocketnet.app/api/v1/videos/6b93423c-531b-4ca6-9ae9-2cf9d84ca41d"
      },
      "comments_count": 3,
      "comments": [
        {
          "comment_tx_id": 135328347,
          "comment_hash_id": 135328347,
          "video_tx_id": 135318479,
          "author_id": 72412207,
          "parent_comment_tx_id": null,
          "answer_comment_tx_id": null,
          "message": "{\"message\":\"🤷\",\"url\":\"\",\"images\":[],\"info\":\"\"}",
          "timestamp": 1752043408,
          "block_height": 3369465,
          "likes": 1,
          "dislikes": 0,
          "author_address": "PKz9dt5AZFsEyH4rU4qdWiWm1triEs6Zoi",
          "author_name": "Elenavakto",
          "author_avatar": "https://bastyon.com:8092/i/FjLTPmegoXARaVNSvIKOYY.jfif",
          "author_reputation": 275046
        },
        {
          "comment_tx_id": 135356380,
          "comment_hash_id": 135356380,
          "video_tx_id": 135318479,
          "author_id": 62569937,
          "parent_comment_tx_id": null,
          "answer_comment_tx_id": null,
          "message": "{\"message\":\"Это очень опасно.😬\",\"url\":\"\",\"images\":[],\"info\":\"\"}",
          "timestamp": 1752057899,
          "block_height": 3369732,
          "likes": 2,
          "dislikes": 0,
          "author_address": "PWGVFU7P9PHkWTFFZkWCrvKbjvDNNkVkCZ",
          "author_name": "AKMTRUD2025",
          "author_avatar": "https://peertube160.pocketnet.app/images/528a2647338cea6f8534f838bac6c4dd/528a2647338cea6f8534f838bac6c4dd-original.jpg",
          "author_reputation": 40158
        },
        {
          "comment_tx_id": 135603795,
          "comment_hash_id": 135603795,
          "video_tx_id": 135318479,
          "author_id": 73717064,
          "parent_comment_tx_id": null,
          "answer_comment_tx_id": null,
          "message": "{\"message\":\"👍🙂🌹\",\"url\":\"\",\"images\":[],\"info\":\"\"}",
          "timestamp": 1752203849,
          "block_height": 3372192,
          "likes": 1,
          "dislikes": 0,
          "author_address": "PFUyJYnsGBhq4aRvykNHkPv1cnWVVgpKdj",
          "author_name": "Svettika",
          "author_avatar": "https://peertube800.pocketnet.app/images/abcb3d5373f5c3c2e11fafba4db3b457/abcb3d5373f5c3c2e11fafba4db3b457-original.jpg",
          "author_reputation": 381540
        }
      ]
    },
    "bastyonPostLink": "https://bastyon.com/post?s=49b48db85cc7b1a9eb1b90343fe3507c50e8a9a20730f7ee3b5c21c423ef454c"
  }
]
